nuc_led/__init__.py
nuc_led/nuc_led.py
nuc_led-0.2.dist-info/LICENSE
nuc_led-0.2.dist-info/METADATA
nuc_led-0.2.dist-info/WHEEL
nuc_led-0.2.dist-info/top_level.txt
nuc_led-0.2.dist-info/RECORD
