Metadata-Version: 2.1
Name: nuc-led
Version: 0.2
Summary: A python API for control of the front LEDs of Intel NUC7i[x]BN and NUC6CAY NUCs.
Home-page: https://github.com/TomAFrench/intel_nuc_led_python_api
Author: Tom French
Author-email: tom@tomfren.ch
License: Apache 2
Platform: UNKNOWN
Classifier: Programming Language :: Python :: 3
Classifier: License :: OSI Approved :: Apache Software License
Classifier: Operating System :: POSIX :: Linux
